lancium/__init__.py
lancium/api/Data.py
lancium/api/Image.py
lancium/api/Job.py
lancium/api/JobInput.py
lancium/api/Resources.py
lancium/api/__init__.py
lancium/core/ApiResource.py
lancium/core/ApiSession.py
lancium/core/__init__.py
lancium/errors/__init__.py
lancium/errors/auth.py
lancium/errors/common.py
lancium/errors/data.py
lancium/errors/image.py
lancium/errors/job.py
lancium/errors/upload.py
tests/__init__.py
tests/conftest.py
tests/adapters/MockApiAdapter.py
tests/adapters/__init__.py
tests/adapters/test_MockApi.py
lancium_compute_api-1.0.2.dist-info/LICENSE
lancium_compute_api-1.0.2.dist-info/METADATA
lancium_compute_api-1.0.2.dist-info/WHEEL
lancium_compute_api-1.0.2.dist-info/top_level.txt
lancium_compute_api-1.0.2.dist-info/RECORD
