Metadata-Version: 2.1
Name: lancium-compute-api
Version: 1.0.2
Summary: Client Library for Lancium API
Home-page: https://github.com/pypa/sampleproject
Author: Rumit Patel
Author-email: rumit.patel@lancium.com
License: UNKNOWN
Platform: UNKNOWN
Requires-Python: >=3.6
License-File: LICENSE
Requires-Dist: pyjwt
Requires-Dist: requests
Requires-Dist: six
Requires-Dist: urllib3
